pattern/__init__.py
pattern/plot.py
jiit-0.0.1a0.dist-info/LICENSE
jiit-0.0.1a0.dist-info/METADATA
jiit-0.0.1a0.dist-info/WHEEL
jiit-0.0.1a0.dist-info/top_level.txt
jiit-0.0.1a0.dist-info/RECORD
